chromadb_deterministic/__init__.py
chromadb_deterministic/app.py
chromadb_deterministic/config.py
chromadb_deterministic/errors.py
chromadb_deterministic/log_config.yml
chromadb_deterministic/py.typed
chromadb_deterministic/serde.py
chromadb_deterministic/types.py
chromadb_deterministic/api/__init__.py
chromadb_deterministic/api/async_api.py
chromadb_deterministic/api/async_client.py
chromadb_deterministic/api/async_fastapi.py
chromadb_deterministic/api/base_http_client.py
chromadb_deterministic/api/client.py
chromadb_deterministic/api/configuration.py
chromadb_deterministic/api/fastapi.py
chromadb_deterministic/api/segment.py
chromadb_deterministic/api/shared_system_client.py
chromadb_deterministic/api/types.py
chromadb_deterministic/api/models/AsyncCollection.py
chromadb_deterministic/api/models/Collection.py
chromadb_deterministic/api/models/CollectionCommon.py
chromadb_deterministic/auth/__init__.py
chromadb_deterministic/auth/basic_authn/__init__.py
chromadb_deterministic/auth/simple_rbac_authz/__init__.py
chromadb_deterministic/auth/token_authn/__init__.py
chromadb_deterministic/cli/__init__.py
chromadb_deterministic/cli/cli.py
chromadb_deterministic/cli/utils.py
chromadb_deterministic/db/__init__.py
chromadb_deterministic/db/base.py
chromadb_deterministic/db/migrations.py
chromadb_deterministic/db/system.py
chromadb_deterministic/db/impl/__init__.py
chromadb_deterministic/db/impl/sqlite.py
chromadb_deterministic/db/impl/sqlite_pool.py
chromadb_deterministic/db/impl/grpc/client.py
chromadb_deterministic/db/impl/grpc/server.py
chromadb_deterministic/db/mixins/embeddings_queue.py
chromadb_deterministic/db/mixins/sysdb.py
chromadb_deterministic/experimental/density_relevance.ipynb
chromadb_deterministic/ingest/__init__.py
chromadb_deterministic/ingest/impl/utils.py
chromadb_deterministic/logservice/logservice.py
chromadb_deterministic/migrations/__init__.py
chromadb_deterministic/migrations/embeddings_queue/00001-embeddings.sqlite.sql
chromadb_deterministic-0.5.5.post6.dist-info/LICENSE
chromadb_deterministic-0.5.5.post6.dist-info/METADATA
chromadb_deterministic-0.5.5.post6.dist-info/WHEEL
chromadb_deterministic-0.5.5.post6.dist-info/entry_points.txt
chromadb_deterministic-0.5.5.post6.dist-info/top_level.txt
chromadb_deterministic-0.5.5.post6.dist-info/RECORD
