Metadata-Version: 2.2
Name: chromadb_deterministic
Version: 0.5.5.post6
Summary: Chroma with deterministic behavior.
Author-email: Jeff Huber <jeff@trychroma.com>, Anton Troynikov <anton@trychroma.com>
Project-URL: Homepage, https://github.com/luthfibalaka/chroma
Project-URL: Bug Tracker, https://github.com/luthfibalaka/chroma/issues
Classifier: Programming Language :: Python :: 3
Classifier: License :: OSI Approved :: Apache Software License
Classifier: Operating System :: OS Independent
Requires-Python: >=3.8
License-File: LICENSE
Requires-Dist: build>=1.0.3
Requires-Dist: pydantic>=2.10.6
Requires-Dist: chroma-hnswlib>=0.7.6
Requires-Dist: fastapi>=0.115.8
Requires-Dist: uvicorn[standard]>=0.34.0
Requires-Dist: numpy<2.0.0,>=1.26.4
Requires-Dist: posthog>=3.14.2
Requires-Dist: typing_extensions>=4.12.2
Requires-Dist: onnxruntime>=1.20.1
Requires-Dist: opentelemetry-api>=1.30.0
Requires-Dist: opentelemetry-exporter-otlp-proto-grpc>=1.30.0
Requires-Dist: opentelemetry-instrumentation-fastapi>=0.51b0
Requires-Dist: opentelemetry-sdk>=1.30.0
Requires-Dist: tokenizers>=0.21.0
Requires-Dist: pypika>=0.48.9
Requires-Dist: tqdm>=4.67.1
Requires-Dist: overrides>=7.7.0
Requires-Dist: importlib-resources>=6.5.2
Requires-Dist: graphlib_backport>=1.0.3; python_version < "3.9"
Requires-Dist: grpcio>=1.70.0
Requires-Dist: bcrypt>=4.2.1
Requires-Dist: typer>=0.15.1
Requires-Dist: kubernetes>=32.0.1
Requires-Dist: tenacity>=9.0.0
Requires-Dist: PyYAML>=6.0.2
Requires-Dist: mmh3>=5.1.0
Requires-Dist: orjson>=3.10.15
Requires-Dist: httpx>=0.28.1
Requires-Dist: rich>=13.9.4
